chat59/__init__.py
chat59/__main__.py
chat59/main.py
59chat-0.3.7.dist-info/METADATA
59chat-0.3.7.dist-info/WHEEL
59chat-0.3.7.dist-info/entry_points.txt
59chat-0.3.7.dist-info/top_level.txt
59chat-0.3.7.dist-info/RECORD
