Metadata-Version: 2.4
Name: 59chat
Version: 0.3.7
Summary: 59-second zero-trace terminal chat (Ultra-Light Edition)
Home-page: https://github.com/yourusername/59chat
Author: YourName
Requires-Python: >=3.8
Requires-Dist: textual>=0.45.0
Requires-Dist: httpx>=0.25.0
Requires-Dist: pyperclip>=1.8.2
Requires-Dist: plyer>=2.1.0
Dynamic: author
Dynamic: description
Dynamic: description-content-type
Dynamic: home-page
Dynamic: requires-dist
Dynamic: requires-python
Dynamic: summary
